importscan/__init__.py
importscan/scan.py
importscan/tests/__init__.py
importscan/tests/test_importscan.py
importscan/tests/fixtures/__init__.py
importscan/tests/fixtures/module.py
importscan/tests/fixtures/zipped.zip
importscan/tests/fixtures/attributeerror/__init__.py
importscan/tests/fixtures/attributeerror/module.py
importscan/tests/fixtures/attributeerror/module2.py
importscan/tests/fixtures/attributeerror_not_handle_error/__init__.py
importscan/tests/fixtures/attributeerror_not_handle_error/module.py
importscan/tests/fixtures/attributeerror_not_handle_error/module2.py
importscan/tests/fixtures/empty_package/__init__.py
importscan/tests/fixtures/empty_subpackage/__init__.py
importscan/tests/fixtures/empty_subpackage/subpackage/__init__.py
importscan/tests/fixtures/ignore_module/__init__.py
importscan/tests/fixtures/ignore_module/module.py
importscan/tests/fixtures/ignore_module_absolute/__init__.py
importscan/tests/fixtures/ignore_module_absolute/module.py
importscan/tests/fixtures/ignore_module_function/__init__.py
importscan/tests/fixtures/ignore_module_function/module.py
importscan/tests/fixtures/ignore_subpackage/__init__.py
importscan/tests/fixtures/ignore_subpackage/sub/__init__.py
importscan/tests/fixtures/ignore_subpackage/sub/module.py
importscan/tests/fixtures/ignore_subpackage_function/__init__.py
importscan/tests/fixtures/ignore_subpackage_function/sub/__init__.py
importscan/tests/fixtures/ignore_subpackage_function/sub/module.py
importscan/tests/fixtures/ignore_subpackage_module/__init__.py
importscan/tests/fixtures/ignore_subpackage_module/sub/__init__.py
importscan/tests/fixtures/ignore_subpackage_module/sub/module.py
importscan/tests/fixtures/importerror/__init__.py
importscan/tests/fixtures/importerror/module.py
importscan/tests/fixtures/importerror/module2.py
importscan/tests/fixtures/importerror_handle_error/__init__.py
importscan/tests/fixtures/importerror_handle_error/module.py
importscan/tests/fixtures/importerror_handle_error/module2.py
importscan-0.2.dist-info/LICENSE.txt
importscan-0.2.dist-info/METADATA
importscan-0.2.dist-info/WHEEL
importscan-0.2.dist-info/top_level.txt
importscan-0.2.dist-info/RECORD
