Metadata-Version: 2.1
Name: importscan
Version: 0.2
Summary: Recursively import modules and sub-packages
Home-page: http://importscan.readthedocs.io
Author: Martijn Faassen
Author-email: faassen@startifact.com
License: BSD
Keywords: decorator import package
Platform: UNKNOWN
Classifier: Intended Audience :: Developers
Classifier: Programming Language :: Python
Classifier: Programming Language :: Python :: 3.4
Classifier: Programming Language :: Python :: 3.5
Classifier: Programming Language :: Python :: 3.6
Classifier: Programming Language :: Python :: 3.7
Classifier: Programming Language :: Python :: 3.8
Classifier: Programming Language :: Python :: Implementation :: CPython
Classifier: Programming Language :: Python :: Implementation :: PyPy
Requires-Dist: setuptools
Provides-Extra: coverage
Requires-Dist: pytest-cov ; extra == 'coverage'
Provides-Extra: pep8
Requires-Dist: flake8 ; extra == 'pep8'
Requires-Dist: black ; extra == 'pep8'
Provides-Extra: test
Requires-Dist: pytest (>=2.9.0) ; extra == 'test'
Requires-Dist: pytest-remove-stale-bytecode ; extra == 'test'
